casify/__init__.py
casify/abc.py
casify/algebra.py
casify/equation.py
casify/function.py
casify/funksjon.py
casify/likning.py
casify/printing.py
casify/regresjon.py
casify/regression.py
casify/symbols.py
casify/triangle.py
casify/vector.py
casify/vektor.py
casify-0.6.18.dist-info/licenses/LICENSE
casify-0.6.18.dist-info/METADATA
casify-0.6.18.dist-info/WHEEL
casify-0.6.18.dist-info/top_level.txt
casify-0.6.18.dist-info/RECORD
