Metadata-Version: 2.4
Name: casify
Version: 0.6.18
Summary: A CAS-library wrapped around sympy to simplify use of CAS-functionality in mathematics.
Home-page: https://github.com/reneaas/casify
Author: René Alexander Ask
Author-email: rene.ask@icloud.com
Classifier: Programming Language :: Python :: 3
Classifier: License :: OSI Approved :: MIT License
Classifier: Operating System :: OS Independent
Requires-Python: >=3.7
License-File: LICENSE
Requires-Dist: sympy
Requires-Dist: plotmath>=0.2.17
Requires-Dist: numpy
Requires-Dist: scipy
Requires-Dist: signchart
Dynamic: author
Dynamic: author-email
Dynamic: classifier
Dynamic: description
Dynamic: description-content-type
Dynamic: home-page
Dynamic: license-file
Dynamic: requires-dist
Dynamic: requires-python
Dynamic: summary
